nonebot_plugin_shindan/__init__.py
nonebot_plugin_shindan/config.py
nonebot_plugin_shindan/manager.py
nonebot_plugin_shindan/migrations/0b2f6bf54834_set_default_value.py
nonebot_plugin_shindan/migrations/3a0f19b79fb5_init_db.py
nonebot_plugin_shindan/migrations/fdc15c338ecc_shindan_id_type.py
nonebot_plugin_shindan/model.py
nonebot_plugin_shindan/shindanmaker.py
nonebot_plugin_shindan/templates/app.css
nonebot_plugin_shindan/templates/app.js
nonebot_plugin_shindan/templates/chart.js
nonebot_plugin_shindan/templates/shindan.html
nonebot_plugin_shindan/templates/shindan_list.html
nonebot_plugin_shindan-0.6.5.dist-info/LICENSE
nonebot_plugin_shindan-0.6.5.dist-info/METADATA
nonebot_plugin_shindan-0.6.5.dist-info/WHEEL
nonebot_plugin_shindan-0.6.5.dist-info/RECORD
