Metadata-Version: 2.1
Name: nonebot_plugin_shindan
Version: 0.6.5
Summary: Nonebot2 plugin for using ShindanMaker
Home-page: https://github.com/noneplugin/nonebot-plugin-shindan
License: MIT
Author: meetwq
Author-email: meetwq@gmail.com
Requires-Python: >=3.9,<4.0
Classifier: License :: OSI Approved :: MIT License
Classifier: Programming Language :: Python :: 3
Classifier: Programming Language :: Python :: 3.9
Classifier: Programming Language :: Python :: 3.10
Classifier: Programming Language :: Python :: 3.11
Classifier: Programming Language :: Python :: 3.12
Classifier: Programming Language :: Python :: 3.13
Requires-Dist: Jinja2 (>=3.0.0,<4.0.0)
Requires-Dist: beautifulsoup4 (>=4.0.0,<5.0.0)
Requires-Dist: httpx (>=0.20.0,<1.0.0)
Requires-Dist: lxml (>=5.0.0,<6.0.0)
Requires-Dist: nonebot-plugin-alconna (>=0.46.3,<1.0.0)
Requires-Dist: nonebot-plugin-htmlrender (>=0.4.0,<0.5.0)
Requires-Dist: nonebot-plugin-orm (>=0.7.0,<1.0.0)
Requires-Dist: nonebot-plugin-uninfo (>=0.4.0,<1.0.0)
Requires-Dist: nonebot2 (>=2.3.0,<3.0.0)
Project-URL: Repository, https://github.com/noneplugin/nonebot-plugin-shindan
